cbz_reader/__main__.py
cbz_reader/static/style.css
cbz_reader/templates/base.html
cbz_reader/templates/list_cbz.html
cbz_reader/templates/load_cbz.html
cbz_reader-1.0.0.dist-info/LICENSE
cbz_reader-1.0.0.dist-info/METADATA
cbz_reader-1.0.0.dist-info/WHEEL
cbz_reader-1.0.0.dist-info/RECORD
